transduction/__init__.py
transduction/tt.py
transduction/util.py
transduction-0.1.3.dist-info/METADATA
transduction-0.1.3.dist-info/WHEEL
transduction-0.1.3.dist-info/licenses/LICENSE
transduction-0.1.3.dist-info/RECORD
