Metadata-Version: 2.1
Name: transduction
Version: 0.1.3
Summary: A package for performing pattern-matching and tree transduction in Python.
Project-URL: Homepage, https://github.com/bkane2/transduction
Project-URL: Bug Tracker, https://github.com/bkane2/transduction/issues
Author-email: Benjamin Kane <Ben.Kane@me.com>
License-File: LICENSE
Classifier: License :: OSI Approved :: MIT License
Classifier: Operating System :: OS Independent
Classifier: Programming Language :: Python :: 3
Requires-Python: >=3.7
